{
  "version": "1",
  "ptp_sync": true,
  "cameras": [
    {
      "serial" : "220700207"
    },
    {
      "serial" : "213902307"
    },
    {
      "serial" : "213902309"
    }
  ],
  "shared_params": [
    {"name": "AcquisitionMode", "value": "Continuous"},
    {"name": "ExposureAuto", "value": "Continuous"},
    {"name": "GainAuto", "value": "Off"},
    {"name": "ExposureTime", "value": 50000},
    {"name": "Gain", "value": 0.0},
    {"name": "AcquisitionFrameRateEnable", "value": true, "val_type": "bool"},
    {"name": "AcquisitionFrameRate", "value": 1.0}
  ]
}